nendo_plugin_quantize_core/__init__.py
nendo_plugin_quantize_core/config.py
nendo_plugin_quantize_core/plugin.py
nendo_plugin_quantize_core-0.2.6.dist-info/LICENSE
nendo_plugin_quantize_core-0.2.6.dist-info/METADATA
nendo_plugin_quantize_core-0.2.6.dist-info/WHEEL
nendo_plugin_quantize_core-0.2.6.dist-info/RECORD
