Metadata-Version: 2.1
Name: nendo-plugin-quantize-core
Version: 0.2.6
Summary: Nendo Plugin for audio quantization with grid detection and time-stretching
Home-page: https://okio.ai
License: GPL-3.0-only
Keywords: Nendo,AI,Machine Learning,Audio,Generative,Music,Audio Production,Audio Generation,Audio Analysis,Quantization,Plugin
Author: Aaron Abebe
Author-email: aaron@okio.ai
Requires-Python: >=3.8,<3.11
Classifier: Development Status :: 5 - Production/Stable
Classifier: Intended Audience :: Developers
Classifier: License :: OSI Approved :: GNU General Public License v3 (GPLv3)
Classifier: Operating System :: OS Independent
Classifier: Programming Language :: Python :: 3
Classifier: Programming Language :: Python :: 3.8
Classifier: Programming Language :: Python :: 3.9
Classifier: Programming Language :: Python :: 3.10
Classifier: Topic :: Multimedia :: Sound/Audio
Requires-Dist: essentia (>=2.1b6.dev1110,<3.0)
Requires-Dist: nendo (>=0.2.0,<0.3.0)
Requires-Dist: pydantic (>=2.0.0,<2.5.0)
Requires-Dist: pydantic-settings (>=2.1.0,<3.0.0)
Requires-Dist: pyrubberband (>=0.3.0,<0.4.0)
Project-URL: Repository, https://github.com/okio-ai/nendo_plugin_quantize_core
